{
    "version": "https://jsonfeed.org/version/1",
    "title": "Ben Fox's Blog",
    "home_page_url": "https://nullfox.com",
    "feed_url": "https://nullfox.com/rss/feed.json",
    "description": "Tips, tricks and guides for TypeScript, web application development and the cloud",
    "icon": "https://nullfox.com/images/logo.png",
    "items": [
        {
            "id": "https://nullfox.com/multiple-exports-typescript-package-types",
            "content_html": "<p>\n      <a href=\"https://nullfox.com/multiple-exports-typescript-package-types\">\n        <img src=\"/images/posts/types.jpg\" width=\"696\">\n      </a>\n    </p>\n    <p>\n      Supporting multiple exports with full type declarations in a Typescript package isn't always straightforward.\n    </p>",
            "url": "https://nullfox.com/multiple-exports-typescript-package-types",
            "title": "Multiple exports with types in a Typescript Package",
            "summary": "<p>\n      <a href=\"https://nullfox.com/multiple-exports-typescript-package-types\">\n        <img src=\"/images/posts/types.jpg\" width=\"696\">\n      </a>\n    </p>\n    <p>\n      Supporting multiple exports with full type declarations in a Typescript package isn't always straightforward.\n    </p>",
            "date_modified": "2022-07-09T00:00:00.000Z"
        },
        {
            "id": "https://nullfox.com/difference-intersection-union-xor-plain-javascript-es6",
            "content_html": "<p>\n      <a href=\"https://nullfox.com/difference-intersection-union-xor-plain-javascript-es6\">\n        <img src=\"/images/posts/card-deck.jpg\" width=\"696\">\n      </a>\n    </p>\n    <p>\n      Skip lodash and up your game with 0 dependency solutions for array filtering, diffing & union-ing\n    </p>",
            "url": "https://nullfox.com/difference-intersection-union-xor-plain-javascript-es6",
            "title": "Implementing difference, intersection, union and xor in ES6 javascript",
            "summary": "<p>\n      <a href=\"https://nullfox.com/difference-intersection-union-xor-plain-javascript-es6\">\n        <img src=\"/images/posts/card-deck.jpg\" width=\"696\">\n      </a>\n    </p>\n    <p>\n      Skip lodash and up your game with 0 dependency solutions for array filtering, diffing & union-ing\n    </p>",
            "date_modified": "2022-06-18T00:00:00.000Z"
        }
    ]
}